lurkmoar
