Metadata-Version: 1.0
Name: lurkmoar
Version: 1.0.2
Summary: 4chan API wrapper geared towards text analysis
Home-page: UNKNOWN
Author: Louis Thibault
Author-email: louist87@gmail.com
License: Unlicense
Keywords: 4chan,b,/b/,imageboard,bbs,text
Platform: UNKNOWN
